{
    "kpis": [
        {
            "id": "voltage",
            "label": "Bus Voltage",
            "value": "28.00V",
            "trend": 0,
            "progress": 93,
            "unit": "V"
        },
        {
            "id": "current",
            "label": "Total Current",
            "value": "4.20A",
            "trend": 0,
            "progress": 42,
            "unit": "A"
        },
        {
            "id": "temp",
            "label": "Core Temp",
            "value": "35.0°C",
            "trend": 0,
            "progress": 35,
            "unit": "°C"
        },
        {
            "id": "gyro",
            "label": "Gyro Stability",
            "value": "0.0001",
            "trend": 0,
            "progress": 99,
            "unit": "rad/s"
        },
        {
            "id": "wheel_speed",
            "label": "Wheel Speed",
            "value": "1200",
            "trend": 0,
            "progress": 60,
            "unit": "rpm"
        },
        {
            "id": "latency",
            "label": "Comm Latency",
            "value": "42ms",
            "trend": 0,
            "progress": 95,
            "unit": "ms"
        }
    ],
    "services": [
        "DB",
        "Telemetry",
        "Ingestion",
        "Cache",
        "API",
        "Worker"
    ],
    "breakers": [
        {
            "from": "DB",
            "to": "Telemetry",
            "state": "Tripped",
            "duration": "14m32s",
            "reason": "Timeout"
        },
        {
            "from": "Cache",
            "to": "API",
            "state": "Half",
            "duration": "2m15s",
            "reason": "High Latency"
        }
    ]
}